disfin/__init__.py
disfin/myfunctions.py
disfin-0.1.0.dist-info/METADATA
disfin-0.1.0.dist-info/WHEEL
disfin-0.1.0.dist-info/top_level.txt
disfin-0.1.0.dist-info/RECORD
