Metadata-Version: 2.1
Name: disfin
Version: 0.1.0
Summary: distance finder library
Author: Oluwaminisholaeniyanko Akanni
License: NCI
